{"type": "FeatureCollection", "features": [{"type": "Feature", "geometry": {"type": "Point", "coordinates": [-71.58915375499998, -34.04150155587557, 0, -1.7976931348623157e+308]}, "properties": {"CODATRAC": "R060072", "JERARQUIA": "NACIONAL", "CATEGORIA": "REALIZACIONES T\u00c9CNICAS Y CIENT\u00cdFICAS CONTEMPOR\u00c1NEAS Y CULTURALES HIST\u00d3RICAS", "TIPO": "OBRAS DE ARTE Y T\u00c9CNICA", "SUBTIPO": "OBRA DE INGENIER\u00cdA", "NOMBRE": "CENTRAL HIDROEL\u00c9CTRICA RAPEL", "REGION": "REGI\u00d3N DEL LIBERTADOR BERNARDO O'HIGGINS", "PROVINCIA": "CARDENAL CARO", "COMUNA": "LITUECHE", "LOCALIDAD": "CENTRAL RAPEL", "DIRECCION": "A 10 KM AL NORTE DE LITUECHE", "TELEFONO": "(2) 22226938", "PROPIEDAD": "PRIVADA", "ADMINISTRA": "PRIVADA", "DISTCR": "186", "CR": "RANCAGUA", "DISTCC": "10", "CC": "LITUECHE", "LOC_URBANA": "LITUECHE", "ESTACIONAL": "TODO EL A\u00d1O", "USO_TUR": "ACTUAL", "DEMANDA": "LOCAL, REGIONAL, NACIONAL", "SERVICIOS": "AGUA POTABLE, ELECTRICIDAD", "COD_REG": 6, "COD_PROV": 62, "COD_COM": 6203, "DESCRIPCIO": "La Central hidroel\u00e9ctrica Rapel, construida en 1968. Da origen a uno de los lagos artificiales m\u00e1s visitados de la zona central del pa\u00eds, el Lago Rapel. La estructura est\u00e1 compuesta por un muro de presa que es una b\u00f3veda de hormig\u00f3n.", "ESTADO_1": "BUENA", "POINT_X": -71.589153755, "POINT_Y": -34.0415015559}}, {"type": "Feature", "geometry": {"type": "Point", "coordinates": [-71.72979243399993, -34.11560743387649, 0, -1.7976931348623157e+308]}, "properties": {"CODATRAC": "R060176", "JERARQUIA": "LOCAL", "CATEGORIA": "ACONTECIMIENTOS PROGRAMADOS", "TIPO": "EVENTOS MISCEL\u00c1NEOS", "SUBTIPO": "CARNAVAL O FIESTA COSTUMBRISTA", "NOMBRE": "FIESTA DEL CORDERO DE LITUECHE", "REGION": "REGI\u00d3N DEL LIBERTADOR BERNARDO O'HIGGINS", "PROVINCIA": "CARDENAL CARO", "COMUNA": "LITUECHE", "LOCALIDAD": "LITUECHE", "DIRECCION": "MEDIALUNA CLUB DE RODEOS, LITUECHE", "TELEFONO": "(72) 2585602", "PROPIEDAD": "P\u00daBLICA", "ADMINISTRA": "P\u00daBLICA", "DISTCR": "169", "CR": "RANCAGUA", "DISTCC": "0", "CC": "LITUECHE", "LOC_URBANA": "LITUECHE", "ESTACIONAL": "NOVIEMBRE", "USO_TUR": "ACTUAL", "DEMANDA": "LOCAL", "SERVICIOS": "AGUA POTABLE, ELECTRICIDAD", "COD_REG": 6, "COD_PROV": 62, "COD_COM": 6203, "DESCRIPCIO": "Esta actividad que en los \u00faltimos a\u00f1os ha ido alcanzando un gran nivel, busca consolidarse como una de las m\u00e1s atractivas de la Regi\u00f3n, para lo que contempla una muestra ganadera, degustaciones culinarias, exposiciones de artesan\u00eda de la zona.", "ESTADO_1": "BUENA", "POINT_X": -71.729792434, "POINT_Y": -34.1156074339}}, {"type": "Feature", "geometry": {"type": "Point", "coordinates": [-71.98747371499996, -34.12699248887659, 0, -1.7976931348623157e+308]}, "properties": {"CODATRAC": "R060315", "JERARQUIA": "REGIONAL", "CATEGORIA": "SITIOS NATURALES", "TIPO": "COSTA", "SUBTIPO": "PLAYA O BALNEARIO", "NOMBRE": "PLAYA TOPOCALMA", "REGION": "REGI\u00d3N DEL LIBERTADOR BERNARDO O'HIGGINS", "PROVINCIA": "CARDENAL CARO", "COMUNA": "LITUECHE", "LOCALIDAD": "TOPOCALMA", "DIRECCION": "A 25 KM AL SUROESTE DE LITUECHE", "TELEFONO": "(72) 2585602", "PROPIEDAD": "P\u00daBLICA", "ADMINISTRA": "P\u00daBLICA", "DISTCR": "205", "CR": "RANCAGUA", "DISTCC": "25", "CC": "LITUECHE", "LOC_URBANA": "LITUECHE", "ESTACIONAL": "TODO EL A\u00d1O", "USO_TUR": "ACTUAL", "DEMANDA": "LOCAL, REGIONAL", "SERVICIOS": "SIN SERVICIOS", "COD_REG": 6, "COD_PROV": 62, "COD_COM": 6203, "DESCRIPCIO": "Topocalma es una playa muy exigente con viento arrachado y olas que corren mucho. Una vista panor\u00e1mica desde un cerro, da una perspectiva de los casi cinco kil\u00f3metros de largo de la playa que cuenta con hermosos bosques y una tranquilidad \u00fanica.", "ESTADO_1": "BUENA", "POINT_X": -71.987473715, "POINT_Y": -34.1269924889}}]}