{"type": "FeatureCollection", "features": [{"type": "Feature", "geometry": {"type": "Point", "coordinates": [-71.26946917399994, -35.05528433888745, 0, -1.7976931348623157e+308]}, "properties": {"CODATRAC": "R070034", "JERARQUIA": "REGIONAL", "CATEGORIA": "ACONTECIMIENTOS PROGRAMADOS", "TIPO": "EVENTOS MISCEL\u00c1NEOS", "SUBTIPO": "CARNAVAL O FIESTA COSTUMBRISTA", "NOMBRE": "CARNAVAL DEL VINO DE LONTUE", "REGION": "REGI\u00d3N DEL MAULE", "PROVINCIA": "CURIC\u00d3", "COMUNA": "MOLINA", "LOCALIDAD": "LONTUE", "DIRECCION": "A 8 KM DE MOLINA", "TELEFONO": "(75) 2543306", "PROPIEDAD": "PRIVADA", "ADMINISTRA": "PRIVADA", "DISTCR": "56", "CR": "TALCA", "DISTCC": "8", "CC": "MOLINA", "LOC_URBANA": "MOLINA", "ESTACIONAL": "MARZO-ABRIL", "USO_TUR": "BUENA", "DEMANDA": "LOCAL, REGIONAL", "SERVICIOS": "AGUA POTABLE, ELECTRICIDAD", "COD_REG": 7, "COD_PROV": 73, "COD_COM": 7304, "DESCRIPCIO": "Es uno de los eventos m\u00e1s importantes de la Provincia. De 4 d\u00edas de duraci\u00f3n y organizado como parte de la culminaci\u00f3n de la temporada de la vendimia. Cuenta con espect\u00e1culos art\u00edsticos y gastronom\u00eda t\u00edpica.", "ESTADO_1": "BUENO", "POINT_X": -71.269469174, "POINT_Y": -35.0552843389}}, {"type": "Feature", "geometry": {"type": "Point", "coordinates": [-70.83249775799999, -35.496478237892255, 0, -1.7976931348623157e+308]}, "properties": {"CODATRAC": "R070049", "JERARQUIA": "REGIONAL", "CATEGORIA": "SITIOS NATURALES", "TIPO": "MONTA\u00d1A", "SUBTIPO": "CERRO", "NOMBRE": "CERRO COLMILLO DEL DIABLO", "REGION": "REGI\u00d3N DEL MAULE", "PROVINCIA": "CURIC\u00d3", "COMUNA": "MOLINA", "LOCALIDAD": "PARQUE NACIONAL RADAL SIETE TAZAS", "DIRECCION": "", "TELEFONO": "", "PROPIEDAD": "P\u00daBLICA", "ADMINISTRA": "P\u00daBLICA", "DISTCR": "0", "CR": "TALCA", "DISTCC": "0", "CC": "", "LOC_URBANA": "", "ESTACIONAL": "DICIEMBRE A MARZO", "USO_TUR": "REGULAR", "DEMANDA": "LOCAL, REGIONAL", "SERVICIOS": "SIN SERVICIOS", "COD_REG": 7, "COD_PROV": 73, "COD_COM": 7304, "DESCRIPCIO": "Recibe su nombre puesto que se alza como un verdadero colmillo rocoso por sobre el Bols\u00f3n. Se encuentra situado en la ribera norte del r\u00edo Claro, cerca de donde \u00e9ste da inicio al llamado valle del Indio.", "ESTADO_1": "BUENO", "POINT_X": -70.832497758, "POINT_Y": -35.4964782379}}, {"type": "Feature", "geometry": {"type": "Point", "coordinates": [-71.03552700899996, -35.528888832892584, 0, -1.7976931348623157e+308]}, "properties": {"CODATRAC": "R070050", "JERARQUIA": "REGIONAL", "CATEGORIA": "SITIOS NATURALES", "TIPO": "MONTA\u00d1A", "SUBTIPO": "CERRO", "NOMBRE": "CERRO EL PICAZO", "REGION": "REGI\u00d3N DEL MAULE", "PROVINCIA": "CURIC\u00d3", "COMUNA": "MOLINA", "LOCALIDAD": "EL RADAL", "DIRECCION": "", "TELEFONO": "", "PROPIEDAD": "P\u00daBLICA", "ADMINISTRA": "P\u00daBLICA", "DISTCR": "0", "CR": "TALCA", "DISTCC": "0", "CC": "", "LOC_URBANA": "", "ESTACIONAL": "DICIEMBRE A ABRIL", "USO_TUR": "REGULAR", "DEMANDA": "LOCAL, REGIONAL", "SERVICIOS": "SIN SERVICIOS", "COD_REG": 7, "COD_PROV": 73, "COD_COM": 7304, "DESCRIPCIO": "Forma parte del cord\u00f3n del Guamparo, que con una orientaci\u00f3n Este-Oeste, separa las RN de Radal Siete Tazas, por el Sur, de la de Altos de Lircay, por el Norte.", "ESTADO_1": "BUENO", "POINT_X": -71.035527009, "POINT_Y": -35.5288888329}}, {"type": "Feature", "geometry": {"type": "Point", "coordinates": [-70.82444799699994, -35.474174495891994, 0, -1.7976931348623157e+308]}, "properties": {"CODATRAC": "R070053", "JERARQUIA": "REGIONAL", "CATEGORIA": "SITIOS NATURALES", "TIPO": "MONTA\u00d1A", "SUBTIPO": "CERRO", "NOMBRE": "CERRO LAS ANIMAS", "REGION": "REGI\u00d3N DEL MAULE", "PROVINCIA": "CURIC\u00d3", "COMUNA": "MOLINA", "LOCALIDAD": "PARQUE NACIONAL RADAL SIETE TAZAS", "DIRECCION": "", "TELEFONO": "", "PROPIEDAD": "P\u00daBLICA", "ADMINISTRA": "P\u00daBLICA", "DISTCR": "125", "CR": "TALCA", "DISTCC": "0", "CC": "", "LOC_URBANA": "", "ESTACIONAL": "DICIEMBRE A MARZO", "USO_TUR": "REGULAR", "DEMANDA": "LOCAL, REGIONAL", "SERVICIOS": "SIN SERVICIOS", "COD_REG": 7, "COD_PROV": 73, "COD_COM": 7304, "DESCRIPCIO": "A pesar de su moderada altura ofrece grandiosas vistas de las monta\u00f1as de la zona. Se encuentra cubierto de una capa de ceniza que le imprime su color caracter\u00edstico y que a la distancia podr\u00eda confundirse con nieve.", "ESTADO_1": "BUENO", "POINT_X": -70.824447997, "POINT_Y": -35.4741744959}}, {"type": "Feature", "geometry": {"type": "Point", "coordinates": [-70.72255537999996, -35.54382813389276, 0, -1.7976931348623157e+308]}, "properties": {"CODATRAC": "R070054", "JERARQUIA": "REGIONAL", "CATEGORIA": "SITIOS NATURALES", "TIPO": "MONTA\u00d1A", "SUBTIPO": "CERRO", "NOMBRE": "CERRO MANANTIAL PELADO", "REGION": "REGI\u00d3N DEL MAULE", "PROVINCIA": "CURIC\u00d3", "COMUNA": "MOLINA", "LOCALIDAD": "", "DIRECCION": "", "TELEFONO": "", "PROPIEDAD": "P\u00daBLICA", "ADMINISTRA": "P\u00daBLICA", "DISTCR": "0", "CR": "TALCA", "DISTCC": "0", "CC": "", "LOC_URBANA": "", "ESTACIONAL": "DICIEMBRE A MARZO", "USO_TUR": "REGULAR", "DEMANDA": "LOCAL, REGIONAL", "SERVICIOS": "SIN SERVICIOS", "COD_REG": 7, "COD_PROV": 73, "COD_COM": 7304, "DESCRIPCIO": "Se ubica al norte del volc\u00e1n Descabezado Grande y al oriente del PN Radal Siete Tazas, en el sector donde nace el r\u00edo Claro. La cuenca que se forma inmediatamente al sur de la monta\u00f1a, alberga una pr\u00edstina laguna conocida con el mismo nombre.", "ESTADO_1": "BUENO", "POINT_X": -70.72255538, "POINT_Y": -35.5438281339}}, {"type": "Feature", "geometry": {"type": "Point", "coordinates": [-71.27981788699998, -35.11396634188811, 0, -1.7976931348623157e+308]}, "properties": {"CODATRAC": "R070098", "JERARQUIA": "REGIONAL", "CATEGORIA": "ACONTECIMIENTOS PROGRAMADOS", "TIPO": "EVENTOS MISCEL\u00c1NEOS", "SUBTIPO": "CARNAVAL O FIESTA COSTUMBRISTA", "NOMBRE": "FESTIVAL DE LA VENDIMIA DE MOLINA", "REGION": "REGI\u00d3N DEL MAULE", "PROVINCIA": "CURIC\u00d3", "COMUNA": "MOLINA", "LOCALIDAD": "MOLINA", "DIRECCION": "", "TELEFONO": "(75) 2543509", "PROPIEDAD": "PRIVADA", "ADMINISTRA": "PRIVADA", "DISTCR": "50", "CR": "TALCA", "DISTCC": "0", "CC": "MOLINA", "LOC_URBANA": "MOLINA", "ESTACIONAL": "MARZO", "USO_TUR": "BUENA", "DEMANDA": "LOCAL, REGIONAL", "SERVICIOS": "AGUA POTABLE, ELECTRICIDAD", "COD_REG": 7, "COD_PROV": 73, "COD_COM": 7304, "DESCRIPCIO": "Es una competencia musical de canciones folcl\u00f3ricas originales. Dicho evento mantiene y fortalece las tradiciones del folklore chileno.", "ESTADO_1": "BUENO", "POINT_X": -71.279817887, "POINT_Y": -35.1139663419}}, {"type": "Feature", "geometry": {"type": "Point", "coordinates": [-70.75900268699996, -35.45834177689182, 0, -1.7976931348623157e+308]}, "properties": {"CODATRAC": "R070162", "JERARQUIA": "LOCAL", "CATEGORIA": "SITIOS NATURALES", "TIPO": "CUERPOS Y CURSOS DE AGUA", "SUBTIPO": "LAGO Y LAGUNA", "NOMBRE": "LAGUNAS DE MONDACA", "REGION": "REGI\u00d3N DEL MAULE", "PROVINCIA": "CURIC\u00d3", "COMUNA": "MOLINA", "LOCALIDAD": "MONDACA", "DIRECCION": "", "TELEFONO": "(75) 2543407", "PROPIEDAD": "P\u00daBLICA", "ADMINISTRA": "P\u00daBLICA", "DISTCR": "130", "CR": "TALCA", "DISTCC": "78", "CC": "MOLINA", "LOC_URBANA": "", "ESTACIONAL": "ENERO A ABRIL", "USO_TUR": "BUENA", "DEMANDA": "LOCAL", "SERVICIOS": "SIN SERVICIOS", "COD_REG": 7, "COD_PROV": 73, "COD_COM": 7304, "DESCRIPCIO": "", "ESTADO_1": "BUENO", "POINT_X": -70.759002687, "POINT_Y": -35.4583417769}}, {"type": "Feature", "geometry": {"type": "Point", "coordinates": [-70.99214983899998, -35.47374866389203, 0, -1.7976931348623157e+308]}, "properties": {"CODATRAC": "R070193", "JERARQUIA": "REGIONAL", "CATEGORIA": "SITIOS NATURALES", "TIPO": "\u00c1REA PROTEGIDA Y LUGARES DE OBSERVACI\u00d3N DE FLORA Y FAUNA", "SUBTIPO": "LUGAR DE OBSERVACI\u00d3N DE FLORA Y FAUNA", "NOMBRE": "PARQUE INGLES EN MOLINA", "REGION": "REGI\u00d3N DEL MAULE", "PROVINCIA": "CURIC\u00d3", "COMUNA": "MOLINA", "LOCALIDAD": "MOLINA", "DIRECCION": "", "TELEFONO": "(75) 2543306", "PROPIEDAD": "P\u00daBLICA", "ADMINISTRA": "P\u00daBLICA", "DISTCR": "128", "CR": "TALCA", "DISTCC": "0", "CC": "MOLINA", "LOC_URBANA": "MOLINA", "ESTACIONAL": "TODO EL A\u00d1O", "USO_TUR": "BUENA", "DEMANDA": "LOCAL, REGIONAL", "SERVICIOS": "SIN SERVICIOS", "COD_REG": 7, "COD_PROV": 73, "COD_COM": 7304, "DESCRIPCIO": "Es un sector cordillerano donde es posible acampar bajo frondosos \u00e1rboles, o efectuar picnic en las riberas del r\u00edo Claro, que ofrece adem\u00e1s la posibilidad de ba\u00f1arse en sus fr\u00edas y transparentes aguas.", "ESTADO_1": "BUENO", "POINT_X": -70.992149839, "POINT_Y": -35.4737486639}}, {"type": "Feature", "geometry": {"type": "Point", "coordinates": [-70.94928821699995, -35.42886873089155, 0, -1.7976931348623157e+308]}, "properties": {"CODATRAC": "R070194", "JERARQUIA": "NACIONAL", "CATEGORIA": "SITIOS NATURALES", "TIPO": "\u00c1REA PROTEGIDA Y LUGARES DE OBSERVACI\u00d3N DE FLORA Y FAUNA", "SUBTIPO": "\u00c1REA SILVESTRE PROTEGIDA DEL ESTADO (ASPE)", "NOMBRE": "PARQUE NACIONAL RADAL SIETE TAZAS", "REGION": "REGI\u00d3N DEL MAULE", "PROVINCIA": "CURIC\u00d3", "COMUNA": "MOLINA", "LOCALIDAD": "RADAL 7 TAZAS", "DIRECCION": "A 50 KM DE MOLINA", "TELEFONO": "(75) 2543306", "PROPIEDAD": "P\u00daBLICA", "ADMINISTRA": "P\u00daBLICA", "DISTCR": "104", "CR": "TALCA", "DISTCC": "50", "CC": "MOLINA", "LOC_URBANA": "MOLINA", "ESTACIONAL": "TODO EL A\u00d1O", "USO_TUR": "BUENA", "DEMANDA": "LOCAL, REGIONAL, NACIONAL", "SERVICIOS": "SIN SERVICIOS", "COD_REG": 7, "COD_PROV": 73, "COD_COM": 7304, "DESCRIPCIO": "Fue creada en 1981 como \"\u00c1rea de Protecci\u00f3n Ambiental\", y el 14 de octubre de 2008 fue declarada Parque Nacional. Es administrada por CONAF, y est\u00e1 abierto todo el a\u00f1o, sin embargo la principal \u00e9poca de visita es el per\u00edodo estival.", "ESTADO_1": "BUENO", "POINT_X": -70.949288217, "POINT_Y": -35.4288687309}}, {"type": "Feature", "geometry": {"type": "Point", "coordinates": [-71.28347526199997, -35.154681860888566, 0, -1.7976931348623157e+308]}, "properties": {"CODATRAC": "R070240", "JERARQUIA": "NACIONAL", "CATEGORIA": "SITIOS NATURALES", "TIPO": "CUERPOS Y CURSOS DE AGUA", "SUBTIPO": "R\u00cdO Y ESTERO", "NOMBRE": "R\u00cdO CLARO EN MOLINA", "REGION": "REGI\u00d3N DEL MAULE", "PROVINCIA": "CURIC\u00d3", "COMUNA": "MOLINA", "LOCALIDAD": "CORDILLERA MOLINA", "DIRECCION": "A 55 KM DE MOLINA", "TELEFONO": "(71) 2291022", "PROPIEDAD": "P\u00daBLICA", "ADMINISTRA": "P\u00daBLICA", "DISTCR": "105", "CR": "TALCA", "DISTCC": "55", "CC": "MOLINA", "LOC_URBANA": "MOLINA", "ESTACIONAL": "TODO EL A\u00d1O", "USO_TUR": "BUENA", "DEMANDA": "LOCAL, REGIONAL, NACIONAL", "SERVICIOS": "SIN SERVICIOS", "COD_REG": 7, "COD_PROV": 73, "COD_COM": 7304, "DESCRIPCIO": "Considerado como Clase IV-V. Es conocido por las famosas cascadas Siete Tazas y los saltos de agua \u201cEl Velo de la Novia\u201d y \u201cEl Salto de la Leona\u201d. Las cascadas son navegables pero representan un verdadero desaf\u00edo hasta para los m\u00e1s expertos.", "ESTADO_1": "BUENO", "POINT_X": -71.283475262, "POINT_Y": -35.1546818609}}, {"type": "Feature", "geometry": {"type": "Point", "coordinates": [-71.21735717099995, -35.08674636288776, 0, -1.7976931348623157e+308]}, "properties": {"CODATRAC": "R070246", "JERARQUIA": "REGIONAL", "CATEGORIA": "SITIOS NATURALES", "TIPO": "CUERPOS Y CURSOS DE AGUA", "SUBTIPO": "R\u00cdO Y ESTERO", "NOMBRE": "R\u00cdO LONTUE", "REGION": "REGI\u00d3N DEL MAULE", "PROVINCIA": "CURIC\u00d3", "COMUNA": "MOLINA", "LOCALIDAD": "LONTUE", "DIRECCION": "A 50 KM DE LONTUE", "TELEFONO": "(75) 2543407", "PROPIEDAD": "P\u00daBLICA", "ADMINISTRA": "P\u00daBLICA", "DISTCR": "55", "CR": "TALCA", "DISTCC": "10", "CC": "MOLINA", "LOC_URBANA": "LONTUE", "ESTACIONAL": "TODO EL A\u00d1O", "USO_TUR": "BUENA", "DEMANDA": "LOCAL, REGIONAL", "SERVICIOS": "SIN SERVICIOS", "COD_REG": 7, "COD_PROV": 73, "COD_COM": 7304, "DESCRIPCIO": "El r\u00edo Lontue posee una hoya hidrogr\u00e1fica de 2510 Km2 aproximadamente y una extensi\u00f3n de 120 km. Su nacimiento esta situado aguas abajo de la Laguna de Mondaca 95 km al sur oriente de la ciudad de CURIC\u00d3.", "ESTADO_1": "BUENO", "POINT_X": -71.217357171, "POINT_Y": -35.0867463629}}, {"type": "Feature", "geometry": {"type": "Point", "coordinates": [-71.03005618199995, -35.45913469189187, 0, -1.7976931348623157e+308]}, "properties": {"CODATRAC": "R070258", "JERARQUIA": "NACIONAL", "CATEGORIA": "SITIOS NATURALES", "TIPO": "CUERPOS Y CURSOS DE AGUA", "SUBTIPO": "CA\u00cdDA DE AGUA", "NOMBRE": "SALTO DE LA LEONA", "REGION": "REGI\u00d3N DEL MAULE", "PROVINCIA": "CURIC\u00d3", "COMUNA": "MOLINA", "LOCALIDAD": "SALTO DE LA LEONA", "DIRECCION": "A 46 KM DE MOLINA", "TELEFONO": "(71) 2228029", "PROPIEDAD": "P\u00daBLICA", "ADMINISTRA": "P\u00daBLICA", "DISTCR": "100", "CR": "TALCA", "DISTCC": "46", "CC": "MOLINA", "LOC_URBANA": "MOLINA", "ESTACIONAL": "TODO EL A\u00d1O", "USO_TUR": "BUENA", "DEMANDA": "LOCAL, REGIONAL, NACIONAL", "SERVICIOS": "SIN SERVICIOS", "COD_REG": 7, "COD_PROV": 73, "COD_COM": 7304, "DESCRIPCIO": "Es un salto que forma parte de los atractivos del \u00e1rea del Parque Nacional Radal Siete Tazas. La constituci\u00f3n geol\u00f3gica del Valle del R\u00edo Claro, que en este sector escurre en un abrupto caj\u00f3n formado por rocas volc\u00e1nicas de distintas edades.", "ESTADO_1": "BUENO", "POINT_X": -71.030056182, "POINT_Y": -35.4591346919}}, {"type": "Feature", "geometry": {"type": "Point", "coordinates": [-71.04479425199997, -35.43936862889163, 0, -1.7976931348623157e+308]}, "properties": {"CODATRAC": "R070260", "JERARQUIA": "NACIONAL", "CATEGORIA": "SITIOS NATURALES", "TIPO": "CUERPOS Y CURSOS DE AGUA", "SUBTIPO": "CA\u00cdDA DE AGUA", "NOMBRE": "SALTO EL VELO DE LA NOVIA", "REGION": "REGI\u00d3N DEL MAULE", "PROVINCIA": "CURIC\u00d3", "COMUNA": "MOLINA", "LOCALIDAD": "RADAL 7 TAZAS", "DIRECCION": "", "TELEFONO": "(75) 2491406", "PROPIEDAD": "P\u00daBLICA", "ADMINISTRA": "P\u00daBLICA", "DISTCR": "102", "CR": "TALCA", "DISTCC": "52", "CC": "MOLINA", "LOC_URBANA": "MOLINA", "ESTACIONAL": "TODO EL A\u00d1O", "USO_TUR": "BUENA", "DEMANDA": "LOCAL, REGIONAL, NACIONAL", "SERVICIOS": "SIN SERVICIOS", "COD_REG": 7, "COD_PROV": 73, "COD_COM": 7304, "DESCRIPCIO": "De 50 metros de altura. Se encuentra al interior del Parque Nacional Radal 7 Tazas.", "ESTADO_1": "BUENO", "POINT_X": -71.044794252, "POINT_Y": -35.4393686289}}, {"type": "Feature", "geometry": {"type": "Point", "coordinates": [-71.27113529399998, -35.09799279788791, 0, -1.7976931348623157e+308]}, "properties": {"CODATRAC": "R070281", "JERARQUIA": "REGIONAL", "CATEGORIA": "MUSEOS MANIFESTACIONES CULTURALES Y LUGARES DE INTER\u00c9S HIST\u00d3RICO O CULTURAL", "TIPO": "LUGAR O SITIO HIST\u00d3RICO", "SUBTIPO": "LUGAR O SITIO HIST\u00d3RICO", "NOMBRE": "SITIO HIST\u00d3RICO DE QUECHEREGUAS", "REGION": "REGI\u00d3N DEL MAULE", "PROVINCIA": "CURIC\u00d3", "COMUNA": "MOLINA", "LOCALIDAD": "QUECHEREGUAS", "DIRECCION": "A 5 KM DE MOLINA", "TELEFONO": "(75) 2543407", "PROPIEDAD": "PRIVADA", "ADMINISTRA": "PRIVADA", "DISTCR": "55", "CR": "TALCA", "DISTCC": "5", "CC": "MOLINA", "LOC_URBANA": "MOLINA", "ESTACIONAL": "TODO EL A\u00d1O", "USO_TUR": "REGULAR", "DEMANDA": "LOCAL, REGIONAL", "SERVICIOS": "SIN SERVICIOS", "COD_REG": 7, "COD_PROV": 73, "COD_COM": 7304, "DESCRIPCIO": "Da\u00f1ado por el terremoto del 27/02/2010. Lugar donde se desarroll\u00f3 el Combate de Quechereguas el 15 de marzo de 1818 entre un destacamento del Ej\u00e9rcito patriota y una columna de 800 hombres del Ej\u00e9rcito realista enviado por el virrey del Per\u00fa.", "ESTADO_1": "REGULAR", "POINT_X": -71.271135294, "POINT_Y": -35.0979927979}}, {"type": "Feature", "geometry": {"type": "Point", "coordinates": [-70.99210411699994, -35.47323556689202, 0, -1.7976931348623157e+308]}, "properties": {"CODATRAC": "R070298", "JERARQUIA": "NACIONAL", "CATEGORIA": "RUTAS Y CIRCUITOS TUR\u00cdSTICOS", "TIPO": "OTROS CIRCUITOS TUR\u00cdSTICOS", "SUBTIPO": "OTROS CIRCUITOS TUR\u00cdSTICOS", "NOMBRE": "TRAMO SENDERO DE CHILE RADAL SIETE TAZAS", "REGION": "REGI\u00d3N DEL MAULE", "PROVINCIA": "CURIC\u00d3", "COMUNA": "MOLINA", "LOCALIDAD": "EL RADAL", "DIRECCION": "", "TELEFONO": "(71) 2231191", "PROPIEDAD": "P\u00daBLICA", "ADMINISTRA": "P\u00daBLICA", "DISTCR": "104", "CR": "TALCA", "DISTCC": "50", "CC": "RADAL", "LOC_URBANA": "RADAL", "ESTACIONAL": "TODO EL A\u00d1O", "USO_TUR": "BUENA", "DEMANDA": "LOCAL, REGIONAL, NACIONAL", "SERVICIOS": "SIN SERVICIOS", "COD_REG": 7, "COD_PROV": 73, "COD_COM": 7304, "DESCRIPCIO": "Con sus 15 km de extensi\u00f3n el tramo Parque Ingl\u00e9s-El Bols\u00f3n se ubica dentro de la Reserva Nacional Radal 7 Tazas en la cordillera de la comuna de Molina, conocida postal de agua que en sus 7 escalones del R\u00edo Claro.", "ESTADO_1": "BUENO", "POINT_X": -70.992104117, "POINT_Y": -35.4732355669}}, {"type": "Feature", "geometry": {"type": "Point", "coordinates": [-71.29482475431665, -35.1297692896324, 0, -1.7976931348623157e+308]}, "properties": {"CODATRAC": "R070324", "JERARQUIA": "NACIONAL", "CATEGORIA": "REALIZACIONES T\u00c9CNICAS Y CIENT\u00cdFICAS CONTEMPOR\u00c1NEAS Y CULTURALES HIST\u00d3RICAS", "TIPO": "EXPLOTACI\u00d3N AGROPECUARIA", "SUBTIPO": "VI\u00d1AS Y BODEGAS", "NOMBRE": "VI\u00d1A MILLAM\u00c1N (EL CONDOR)", "REGION": "REGI\u00d3N DEL MAULE", "PROVINCIA": "CURIC\u00d3", "COMUNA": "MOLINA", "LOCALIDAD": "MOLINA", "DIRECCION": "Fundo Peteroa S/N, Sagrada Familia, Curic\u00f3", "TELEFONO": "(56-75) 32 8972", "PROPIEDAD": "PRIVADA", "ADMINISTRA": "PRIVADA", "DISTCR": "52", "CR": "TALCA", "DISTCC": "2", "CC": "MOLINA", "LOC_URBANA": "MOLINA", "ESTACIONAL": "TODO EL A\u00d1O", "USO_TUR": "BUENA", "DEMANDA": "LOCAL, REGIONAL, NACIONAL", "SERVICIOS": "AGUA POTABLE, ELECTRICIDAD", "COD_REG": 7, "COD_PROV": 73, "COD_COM": 7304, "DESCRIPCIO": "Bodega de vinos de paredes de adobe de m\u00e1s de 100 a\u00f1os, fue cuidadosamente restaurada preservando el estilo chileno colonial. Con este hecho se marca el nacimiento de Millam\u00e1n. Se realizan tour a la vi\u00f1a.", "ESTADO_1": "BUENO", "POINT_X": -71.2948247543, "POINT_Y": -35.1297692896}}, {"type": "Feature", "geometry": {"type": "Point", "coordinates": [-71.30212837399995, -35.09994333699996, 0, -1.7976931348623157e+308]}, "properties": {"CODATRAC": "R070316", "JERARQUIA": "NACIONAL", "CATEGORIA": "REALIZACIONES T\u00c9CNICAS Y CIENT\u00cdFICAS CONTEMPOR\u00c1NEAS Y CULTURALES HIST\u00d3RICAS", "TIPO": "EXPLOTACI\u00d3N AGROPECUARIA", "SUBTIPO": "VI\u00d1AS Y BODEGAS", "NOMBRE": "VI\u00d1A ECHEVERR\u00cdA", "REGION": "REGI\u00d3N DEL MAULE", "PROVINCIA": "CURIC\u00d3", "COMUNA": "MOLINA", "LOCALIDAD": "MOLINA", "DIRECCION": "", "TELEFONO": "+ 56 2 23425358", "PROPIEDAD": "PRIVADA", "ADMINISTRA": "PRIVADA", "DISTCR": "48", "CR": "TALCA", "DISTCC": "3", "CC": "MOLINA", "LOC_URBANA": "MOLINA", "ESTACIONAL": "TODO EL A\u00d1O", "USO_TUR": "BUENA", "DEMANDA": "LOCAL, REGIONAL, NACIONAL", "SERVICIOS": "AGUA POTABLE, ELECTRICIDAD", "COD_REG": 7, "COD_PROV": 73, "COD_COM": 7304, "DESCRIPCIO": "Conocida por su producci\u00f3n de uvas nacidas de las mejores cepas de origen franc\u00e9s, probar sus vinos de alta calidad es un privilegio. Realizan tours y degustaciones de mano de un en\u00f3logo de la vi\u00f1a. Tours de lunes a viernes.", "ESTADO_1": "BUENO", "POINT_X": -71.302128374, "POINT_Y": -35.099943337}}]}